[
    {
        "id": "0752450024-1",
        "type": "HALF_PALLET",
        "order_id": "0752450024",
        "demand": 0.5,
        "pickup_factory_id": "2445d4bd004c457d95957d6ecf77f759",
        "delivery_factory_id": "b6dd694ae05541dba369a2a759d2c2b9",
        "creation_time": 1755478365,
        "committed_completion_time": 1755492765,
        "load_time": 120,
        "unload_time": 120,
        "delivery_state": 1
    },
    {
        "id": "0814210026-1",
        "type": "HALF_PALLET",
        "order_id": "0814210026",
        "demand": 0.5,
        "pickup_factory_id": "2445d4bd004c457d95957d6ecf77f759",
        "delivery_factory_id": "f6faef4b36e743328800b961aced4a2c",
        "creation_time": 1755479661,
        "committed_completion_time": 1755494061,
        "load_time": 120,
        "unload_time": 120,
        "delivery_state": 1
    },
    {
        "id": "0840320030-1",
        "type": "HALF_PALLET",
        "order_id": "0840320030",
        "demand": 0.5,
        "pickup_factory_id": "2445d4bd004c457d95957d6ecf77f759",
        "delivery_factory_id": "b6dd694ae05541dba369a2a759d2c2b9",
        "creation_time": 1755481232,
        "committed_completion_time": 1755495632,
        "load_time": 120,
        "unload_time": 120,
        "delivery_state": 1
    },
    {
        "id": "0904360031-1",
        "type": "PALLET",
        "order_id": "0904360031",
        "demand": 1,
        "pickup_factory_id": "5e2e9efa5ade4984bb18af66028bc0c8",
        "delivery_factory_id": "9b40bfd6ca1c432498685540652a5a8b",
        "creation_time": 1755482676,
        "committed_completion_time": 1755497076,
        "load_time": 240,
        "unload_time": 240,
        "delivery_state": 1
    },
    {
        "id": "0908390032-1",
        "type": "PALLET",
        "order_id": "0908390032",
        "demand": 1,
        "pickup_factory_id": "2445d4bd004c457d95957d6ecf77f759",
        "delivery_factory_id": "b6dd694ae05541dba369a2a759d2c2b9",
        "creation_time": 1755482919,
        "committed_completion_time": 1755497319,
        "load_time": 240,
        "unload_time": 240,
        "delivery_state": 1
    },
    {
        "id": "0908390032-2",
        "type": "PALLET",
        "order_id": "0908390032",
        "demand": 1,
        "pickup_factory_id": "2445d4bd004c457d95957d6ecf77f759",
        "delivery_factory_id": "b6dd694ae05541dba369a2a759d2c2b9",
        "creation_time": 1755482919,
        "committed_completion_time": 1755497319,
        "load_time": 240,
        "unload_time": 240,
        "delivery_state": 1
    },
    {
        "id": "0908390032-3",
        "type": "PALLET",
        "order_id": "0908390032",
        "demand": 1,
        "pickup_factory_id": "2445d4bd004c457d95957d6ecf77f759",
        "delivery_factory_id": "b6dd694ae05541dba369a2a759d2c2b9",
        "creation_time": 1755482919,
        "committed_completion_time": 1755497319,
        "load_time": 240,
        "unload_time": 240,
        "delivery_state": 1
    },
    {
        "id": "0908390032-4",
        "type": "PALLET",
        "order_id": "0908390032",
        "demand": 1,
        "pickup_factory_id": "2445d4bd004c457d95957d6ecf77f759",
        "delivery_factory_id": "b6dd694ae05541dba369a2a759d2c2b9",
        "creation_time": 1755482919,
        "committed_completion_time": 1755497319,
        "load_time": 240,
        "unload_time": 240,
        "delivery_state": 1
    },
    {
        "id": "0908390032-5",
        "type": "PALLET",
        "order_id": "0908390032",
        "demand": 1,
        "pickup_factory_id": "2445d4bd004c457d95957d6ecf77f759",
        "delivery_factory_id": "b6dd694ae05541dba369a2a759d2c2b9",
        "creation_time": 1755482919,
        "committed_completion_time": 1755497319,
        "load_time": 240,
        "unload_time": 240,
        "delivery_state": 1
    },
    {
        "id": "0908390032-6",
        "type": "PALLET",
        "order_id": "0908390032",
        "demand": 1,
        "pickup_factory_id": "2445d4bd004c457d95957d6ecf77f759",
        "delivery_factory_id": "b6dd694ae05541dba369a2a759d2c2b9",
        "creation_time": 1755482919,
        "committed_completion_time": 1755497319,
        "load_time": 240,
        "unload_time": 240,
        "delivery_state": 1
    },
    {
        "id": "0908390032-7",
        "type": "HALF_PALLET",
        "order_id": "0908390032",
        "demand": 0.5,
        "pickup_factory_id": "2445d4bd004c457d95957d6ecf77f759",
        "delivery_factory_id": "b6dd694ae05541dba369a2a759d2c2b9",
        "creation_time": 1755482919,
        "committed_completion_time": 1755497319,
        "load_time": 120,
        "unload_time": 120,
        "delivery_state": 1
    },
    {
        "id": "0908390032-8",
        "type": "HALF_PALLET",
        "order_id": "0908390032",
        "demand": 0.5,
        "pickup_factory_id": "2445d4bd004c457d95957d6ecf77f759",
        "delivery_factory_id": "b6dd694ae05541dba369a2a759d2c2b9",
        "creation_time": 1755482919,
        "committed_completion_time": 1755497319,
        "load_time": 120,
        "unload_time": 120,
        "delivery_state": 1
    },
    {
        "id": "0908390032-9",
        "type": "HALF_PALLET",
        "order_id": "0908390032",
        "demand": 0.5,
        "pickup_factory_id": "2445d4bd004c457d95957d6ecf77f759",
        "delivery_factory_id": "b6dd694ae05541dba369a2a759d2c2b9",
        "creation_time": 1755482919,
        "committed_completion_time": 1755497319,
        "load_time": 120,
        "unload_time": 120,
        "delivery_state": 1
    },
    {
        "id": "0908390032-10",
        "type": "HALF_PALLET",
        "order_id": "0908390032",
        "demand": 0.5,
        "pickup_factory_id": "2445d4bd004c457d95957d6ecf77f759",
        "delivery_factory_id": "b6dd694ae05541dba369a2a759d2c2b9",
        "creation_time": 1755482919,
        "committed_completion_time": 1755497319,
        "load_time": 120,
        "unload_time": 120,
        "delivery_state": 1
    },
    {
        "id": "0908390032-11",
        "type": "HALF_PALLET",
        "order_id": "0908390032",
        "demand": 0.5,
        "pickup_factory_id": "2445d4bd004c457d95957d6ecf77f759",
        "delivery_factory_id": "b6dd694ae05541dba369a2a759d2c2b9",
        "creation_time": 1755482919,
        "committed_completion_time": 1755497319,
        "load_time": 120,
        "unload_time": 120,
        "delivery_state": 1
    },
    {
        "id": "0908390032-12",
        "type": "HALF_PALLET",
        "order_id": "0908390032",
        "demand": 0.5,
        "pickup_factory_id": "2445d4bd004c457d95957d6ecf77f759",
        "delivery_factory_id": "b6dd694ae05541dba369a2a759d2c2b9",
        "creation_time": 1755482919,
        "committed_completion_time": 1755497319,
        "load_time": 120,
        "unload_time": 120,
        "delivery_state": 1
    },
    {
        "id": "0908390032-13",
        "type": "HALF_PALLET",
        "order_id": "0908390032",
        "demand": 0.5,
        "pickup_factory_id": "2445d4bd004c457d95957d6ecf77f759",
        "delivery_factory_id": "b6dd694ae05541dba369a2a759d2c2b9",
        "creation_time": 1755482919,
        "committed_completion_time": 1755497319,
        "load_time": 120,
        "unload_time": 120,
        "delivery_state": 1
    },
    {
        "id": "0908390032-14",
        "type": "HALF_PALLET",
        "order_id": "0908390032",
        "demand": 0.5,
        "pickup_factory_id": "2445d4bd004c457d95957d6ecf77f759",
        "delivery_factory_id": "b6dd694ae05541dba369a2a759d2c2b9",
        "creation_time": 1755482919,
        "committed_completion_time": 1755497319,
        "load_time": 120,
        "unload_time": 120,
        "delivery_state": 1
    },
    {
        "id": "0908390032-15",
        "type": "HALF_PALLET",
        "order_id": "0908390032",
        "demand": 0.5,
        "pickup_factory_id": "2445d4bd004c457d95957d6ecf77f759",
        "delivery_factory_id": "b6dd694ae05541dba369a2a759d2c2b9",
        "creation_time": 1755482919,
        "committed_completion_time": 1755497319,
        "load_time": 120,
        "unload_time": 120,
        "delivery_state": 1
    },
    {
        "id": "0908390032-16",
        "type": "HALF_PALLET",
        "order_id": "0908390032",
        "demand": 0.5,
        "pickup_factory_id": "2445d4bd004c457d95957d6ecf77f759",
        "delivery_factory_id": "b6dd694ae05541dba369a2a759d2c2b9",
        "creation_time": 1755482919,
        "committed_completion_time": 1755497319,
        "load_time": 120,
        "unload_time": 120,
        "delivery_state": 1
    },
    {
        "id": "0937160033-1",
        "type": "BOX",
        "order_id": "0937160033",
        "demand": 0.25,
        "pickup_factory_id": "5e2e9efa5ade4984bb18af66028bc0c8",
        "delivery_factory_id": "f6faef4b36e743328800b961aced4a2c",
        "creation_time": 1755484636,
        "committed_completion_time": 1755499036,
        "load_time": 60,
        "unload_time": 60,
        "delivery_state": 1
    },
    {
        "id": "0945340034-1",
        "type": "PALLET",
        "order_id": "0945340034",
        "demand": 1,
        "pickup_factory_id": "2445d4bd004c457d95957d6ecf77f759",
        "delivery_factory_id": "b6dd694ae05541dba369a2a759d2c2b9",
        "creation_time": 1755485134,
        "committed_completion_time": 1755499534,
        "load_time": 240,
        "unload_time": 240,
        "delivery_state": 1
    },
    {
        "id": "0945340034-2",
        "type": "HALF_PALLET",
        "order_id": "0945340034",
        "demand": 0.5,
        "pickup_factory_id": "2445d4bd004c457d95957d6ecf77f759",
        "delivery_factory_id": "b6dd694ae05541dba369a2a759d2c2b9",
        "creation_time": 1755485134,
        "committed_completion_time": 1755499534,
        "load_time": 120,
        "unload_time": 120,
        "delivery_state": 1
    },
    {
        "id": "0945340034-3",
        "type": "HALF_PALLET",
        "order_id": "0945340034",
        "demand": 0.5,
        "pickup_factory_id": "2445d4bd004c457d95957d6ecf77f759",
        "delivery_factory_id": "b6dd694ae05541dba369a2a759d2c2b9",
        "creation_time": 1755485134,
        "committed_completion_time": 1755499534,
        "load_time": 120,
        "unload_time": 120,
        "delivery_state": 1
    },
    {
        "id": "0945340035-1",
        "type": "HALF_PALLET",
        "order_id": "0945340035",
        "demand": 0.5,
        "pickup_factory_id": "2445d4bd004c457d95957d6ecf77f759",
        "delivery_factory_id": "9f1a09c368584eba9e7f10a53d55caae",
        "creation_time": 1755485134,
        "committed_completion_time": 1755499534,
        "load_time": 120,
        "unload_time": 120,
        "delivery_state": 1
    },
    {
        "id": "0945340035-2",
        "type": "BOX",
        "order_id": "0945340035",
        "demand": 0.25,
        "pickup_factory_id": "2445d4bd004c457d95957d6ecf77f759",
        "delivery_factory_id": "9f1a09c368584eba9e7f10a53d55caae",
        "creation_time": 1755485134,
        "committed_completion_time": 1755499534,
        "load_time": 60,
        "unload_time": 60,
        "delivery_state": 1
    },
    {
        "id": "0947260036-1",
        "type": "HALF_PALLET",
        "order_id": "0947260036",
        "demand": 0.5,
        "pickup_factory_id": "f6faef4b36e743328800b961aced4a2c",
        "delivery_factory_id": "5e2e9efa5ade4984bb18af66028bc0c8",
        "creation_time": 1755485246,
        "committed_completion_time": 1755499646,
        "load_time": 120,
        "unload_time": 120,
        "delivery_state": 1
    },
    {
        "id": "0947260036-2",
        "type": "HALF_PALLET",
        "order_id": "0947260036",
        "demand": 0.5,
        "pickup_factory_id": "f6faef4b36e743328800b961aced4a2c",
        "delivery_factory_id": "5e2e9efa5ade4984bb18af66028bc0c8",
        "creation_time": 1755485246,
        "committed_completion_time": 1755499646,
        "load_time": 120,
        "unload_time": 120,
        "delivery_state": 1
    },
    {
        "id": "0957250037-1",
        "type": "HALF_PALLET",
        "order_id": "0957250037",
        "demand": 0.5,
        "pickup_factory_id": "5e2e9efa5ade4984bb18af66028bc0c8",
        "delivery_factory_id": "32ab2049f3fb437881ff3912470d7840",
        "creation_time": 1755485845,
        "committed_completion_time": 1755500245,
        "load_time": 120,
        "unload_time": 120,
        "delivery_state": 1
    },
    {
        "id": "0958190038-1",
        "type": "BOX",
        "order_id": "0958190038",
        "demand": 0.25,
        "pickup_factory_id": "5e2e9efa5ade4984bb18af66028bc0c8",
        "delivery_factory_id": "b6dd694ae05541dba369a2a759d2c2b9",
        "creation_time": 1755485899,
        "committed_completion_time": 1755500299,
        "load_time": 60,
        "unload_time": 60,
        "delivery_state": 1
    },
    {
        "id": "0958190038-2",
        "type": "BOX",
        "order_id": "0958190038",
        "demand": 0.25,
        "pickup_factory_id": "5e2e9efa5ade4984bb18af66028bc0c8",
        "delivery_factory_id": "b6dd694ae05541dba369a2a759d2c2b9",
        "creation_time": 1755485899,
        "committed_completion_time": 1755500299,
        "load_time": 60,
        "unload_time": 60,
        "delivery_state": 1
    },
    {
        "id": "1000330039-1",
        "type": "PALLET",
        "order_id": "1000330039",
        "demand": 1,
        "pickup_factory_id": "2445d4bd004c457d95957d6ecf77f759",
        "delivery_factory_id": "9f1a09c368584eba9e7f10a53d55caae",
        "creation_time": 1755486033,
        "committed_completion_time": 1755500433,
        "load_time": 240,
        "unload_time": 240,
        "delivery_state": 1
    },
    {
        "id": "1002470040-1",
        "type": "BOX",
        "order_id": "1002470040",
        "demand": 0.25,
        "pickup_factory_id": "ffd0ed8719f54294a452ed3e3b6a986c",
        "delivery_factory_id": "9f1a09c368584eba9e7f10a53d55caae",
        "creation_time": 1755486167,
        "committed_completion_time": 1755500567,
        "load_time": 60,
        "unload_time": 60,
        "delivery_state": 1
    }
]